<?xml version="1.0" encoding="UTF-8"?>
<gc:CodeList xmlns:gc="http://docs.oasis-open.org/codelist/ns/genericode/1.0/"
             xmlns:xsi="http://www.w3.org/2001/XMLSchema-instance"
             xmlns:xoev-cl-3="http://xoev.de/schemata/genericode/3">
   <Annotation>
      <Description>
         <xoev-cl-3:nameKurz>Art der Tr채gerschaft</xoev-cl-3:nameKurz>
         <xoev-cl-3:beschreibung-codeliste>Art der Tr채gerschaft</xoev-cl-3:beschreibung-codeliste>
         <xoev-cl-3:herausgebernameKurz>XBildung</xoev-cl-3:herausgebernameKurz>
         <xoev-cl-3:datumGueltigkeitAb>2020-04-26</xoev-cl-3:datumGueltigkeitAb>
         <xoev-cl-3:versionCodelistenHandbuch>1.0</xoev-cl-3:versionCodelistenHandbuch>
         <xoev-cl-3:aenderungZurVorversion>.</xoev-cl-3:aenderungZurVorversion>
      </Description>
   </Annotation>
   <Identification>
      <ShortName>ArtderTraegerschaft-Codes</ShortName>
      <LongName>Art der Tr채gerschaft</LongName>
      <Version>0.7</Version>
      <CanonicalUri>urn:xbildung-de:xbildung:codeliste:artdertraegerschaft</CanonicalUri>
      <CanonicalVersionUri>urn:xbildung-de:xbildung:codeliste:artdertraegerschaft_0.7</CanonicalVersionUri>
      <Agency>
         <LongName>XBildung</LongName>
      </Agency>
   </Identification>
   <ColumnSet>
      <Column Id="code" Use="required">
         <ShortName>code</ShortName>
         <LongName>Code Name</LongName>
         <Data Type="string"/>
      </Column>
      <Column Id="description-de-DE" Use="optional">
         <ShortName>description-de-DE</ShortName>
         <LongName>Tr채gerschaft</LongName>
         <Data Type="string"/>
      </Column>
      <Key Id="codeKey">
         <Annotation>
            <AppInfo>
               <xoev-cl-3:empfohleneCodeSpalte/>
            </AppInfo>
         </Annotation>
         <ShortName>codeKey</ShortName>
         <ColumnRef Ref="code"/>
      </Key>
   </ColumnSet>
   <SimpleCodeList>
      <Row>
         <Value ColumnRef="code">
            <SimpleValue>http://xbildung.de/def/xbildung/0.7/code/ArtDerTraegerschaft/1</SimpleValue>
         </Value>
         <Value ColumnRef="description-de-DE">
            <SimpleValue>Bund</SimpleValue>
         </Value>
      </Row>
      <Row>
         <Value ColumnRef="code">
            <SimpleValue>http://xbildung.de/def/xbildung/0.7/code/ArtDerTraegerschaft/2</SimpleValue>
         </Value>
         <Value ColumnRef="description-de-DE">
            <SimpleValue>Land</SimpleValue>
         </Value>
      </Row>
      <Row>
         <Value ColumnRef="code">
            <SimpleValue>http://xbildung.de/def/xbildung/0.7/code/ArtDerTraegerschaft/3</SimpleValue>
         </Value>
         <Value ColumnRef="description-de-DE">
            <SimpleValue>Kommune</SimpleValue>
         </Value>
      </Row>
      <Row>
         <Value ColumnRef="code">
            <SimpleValue>http://xbildung.de/def/xbildung/0.7/code/ArtDerTraegerschaft/4</SimpleValue>
         </Value>
         <Value ColumnRef="description-de-DE">
            <SimpleValue>Privat</SimpleValue>
         </Value>
      </Row>
      <Row>
         <Value ColumnRef="code">
            <SimpleValue>http://xbildung.de/def/xbildung/0.7/code/ArtDerTraegerschaft/5</SimpleValue>
         </Value>
         <Value ColumnRef="description-de-DE">
            <SimpleValue>Kirchlich</SimpleValue>
         </Value>
      </Row>
      <Row>
         <Value ColumnRef="code">
            <SimpleValue>http://xbildung.de/def/xbildung/0.7/code/ArtDerTraegerschaft/6</SimpleValue>
         </Value>
         <Value ColumnRef="description-de-DE">
            <SimpleValue>Sonstige</SimpleValue>
         </Value>
      </Row>
   </SimpleCodeList>
</gc:CodeList>
